benchadapt/__init__.py
benchadapt/_machine_info.py
benchadapt/_version.py
benchadapt/client.py
benchadapt/log.py
benchadapt/result.py
benchadapt/adapters/__init__.py
benchadapt/adapters/_adapter.py
benchadapt/adapters/archery.py
benchadapt/adapters/asvbench.py
benchadapt/adapters/callable.py
benchadapt/adapters/folly.py
benchadapt/adapters/gbench.py
tests/__init__.py
tests/test_result.py
tests/test_version.py
tests/adapters/__init__.py
tests/adapters/test_adapter.py
tests/adapters/test_archery.py
tests/adapters/test_asvbench.py
tests/adapters/test_callable.py
tests/adapters/test_folly.py
tests/adapters/test_gbench.py
benchadapt-2024.3.20.dist-info/LICENSE.txt
benchadapt-2024.3.20.dist-info/METADATA
benchadapt-2024.3.20.dist-info/WHEEL
benchadapt-2024.3.20.dist-info/top_level.txt
benchadapt-2024.3.20.dist-info/RECORD
