Metadata-Version: 2.1
Name: benchadapt
Version: 2024.3.20
Summary: Adapters for Running and Tracking Benchmarks
Home-page: https://github.com/conbench/conbench/tree/main/benchadapt
Maintainer: Voltron Data
Maintainer-email: conbench@voltrondata.com
Classifier: Programming Language :: Python :: 3.8
Classifier: License :: OSI Approved :: Apache Software License
Requires-Python: >=3.8
License-File: LICENSE.txt
Requires-Dist: benchclients
Requires-Dist: numpy
